confirm/__init__.py
confirm/__main__.py
confirm/confirm.py
confirm/py.typed
cli_confirm-1.0.0.dist-info/entry_points.txt
cli_confirm-1.0.0.dist-info/LICENSE
cli_confirm-1.0.0.dist-info/WHEEL
cli_confirm-1.0.0.dist-info/METADATA
cli_confirm-1.0.0.dist-info/RECORD
